learnbot_components/__init__.py
learnbot_components/description.md
learnbot_components/baserobot/DoxyFile
learnbot_components/baserobot/README.md
learnbot_components/baserobot/__init__.py
learnbot_components/baserobot/baserobot.cdsl
learnbot_components/baserobot/etc/__init__.py
learnbot_components/baserobot/etc/config
learnbot_components/baserobot/src/__init__.py
learnbot_components/baserobot/src/baserobot.py
learnbot_components/baserobot/src/differentialrobotI.py
learnbot_components/baserobot/src/genericworker.py
learnbot_components/baserobot/src/specificworker.py
learnbot_components/camera/__init__.py
learnbot_components/camera/camera.py
learnbot_components/camera/mosquitto.conf
learnbot_components/display/DoxyFile
learnbot_components/display/README.md
learnbot_components/display/__init__.py
learnbot_components/display/display.cdsl
learnbot_components/display/etc/__init__.py
learnbot_components/display/etc/config
learnbot_components/display/etc/config.new
learnbot_components/display/src/__init__.py
learnbot_components/display/src/display.py
learnbot_components/display/src/displayI.py
learnbot_components/display/src/genericworker.py
learnbot_components/display/src/specificworker.py
learnbot_components/emotionalMotor/DoxyFile
learnbot_components/emotionalMotor/README.md
learnbot_components/emotionalMotor/__init__.py
learnbot_components/emotionalMotor/emotionalMotor.cdsl
learnbot_components/emotionalMotor/etc/__init__.py
learnbot_components/emotionalMotor/etc/config
learnbot_components/emotionalMotor/imgs/FelizmenteSorprendido2.png
learnbot_components/emotionalMotor/imgs/Learnbot.png
learnbot_components/emotionalMotor/imgs/Leyenda.JPG
learnbot_components/emotionalMotor/imgs/SinEmocion2.png
learnbot_components/emotionalMotor/imgs/TristementeSorprendido2.png
learnbot_components/emotionalMotor/imgs/__init__.py
learnbot_components/emotionalMotor/imgs/alegria.png
learnbot_components/emotionalMotor/imgs/asco.png
learnbot_components/emotionalMotor/imgs/generate-fb.sh
learnbot_components-0.0.3.dist-info/LICENSE
learnbot_components-0.0.3.dist-info/METADATA
learnbot_components-0.0.3.dist-info/WHEEL
learnbot_components-0.0.3.dist-info/top_level.txt
learnbot_components-0.0.3.dist-info/RECORD
