Metadata-Version: 2.1
Name: learnbot-components
Version: 0.0.3
Summary: learnbot_components contains some components to install in learnbot robot.
Home-page: https://github.com/robocomp/learnbot/tree/version-2-component-pip
Author: Ivan Barbecho
Author-email: ivanbd@unex.es
License: GPL
Platform: UNKNOWN
Requires-Dist: matplotlib (==2.2.2)
Requires-Dist: opencv-python-headless (==3.4.3.18)
Requires-Dist: scipy (==1.0.0)
Requires-Dist: tensorflow (==1.10.1)
Requires-Dist: pandas (==0.19.1)
Requires-Dist: Keras (==2.0.5)
Requires-Dist: h5py (==2.7.0)
Requires-Dist: epitran (==0.4)
Requires-Dist: numpy (==1.13.3)
Requires-Dist: Adafruit-PCA9685 (==1.0.1)
Requires-Dist: ice (==0.0.2)
Requires-Dist: PySide (==1.2.4)
Requires-Dist: paho-mqtt (==1.4.0)
Requires-Dist: picamera (==1.13)
Requires-Dist: wiringpi (==2.46.0)
Requires-Dist: wiringpi2 (==2.32.3)
